hil/can/zlg/kerneldlls/CANDTU_NET.dll
hil/can/zlg/kerneldlls/CANDevCore.dll
hil/can/zlg/kerneldlls/CANDevice.dll
hil/can/zlg/kerneldlls/CANETE.dll
hil/can/zlg/kerneldlls/CANET_TCP.dll
hil/can/zlg/kerneldlls/CANFDCOM.dll
hil/can/zlg/kerneldlls/CANFDNET.dll
hil/can/zlg/kerneldlls/CANWIFI_TCP.dll
hil/can/zlg/kerneldlls/CANWIFI_UDP.dll
hil/can/zlg/kerneldlls/USBCAN.dll
hil/can/zlg/kerneldlls/USBCAN.xml
hil/can/zlg/kerneldlls/USBCANFD.dll
hil/can/zlg/kerneldlls/USBCANFD800U.dll
hil/can/zlg/kerneldlls/VCI_USBCAN2.xml
hil/can/zlg/kerneldlls/VirtualUSBCAN.dll
hil/can/zlg/kerneldlls/ZlgCloud.dll
hil/can/zlg/kerneldlls/__init__.py
hil/can/zlg/kerneldlls/dll_cfg.ini
hil/can/zlg/kerneldlls/devices_property/__init__.py
hil/can/zlg/kerneldlls/devices_property/can.xml
hil/can/zlg/kerneldlls/devices_property/candtu-100ur.xml
hil/can/zlg/kerneldlls/devices_property/candtu-200ur.xml
hil/can/zlg/kerneldlls/devices_property/candtu-net-400.xml
hil/can/zlg/kerneldlls/devices_property/candtu-net.xml
hil/can/zlg/kerneldlls/devices_property/candtu.ini
hil/can/zlg/kerneldlls/devices_property/canet-tcp.xml
hil/can/zlg/kerneldlls/devices_property/canet-udp.xml
hil/can/zlg/kerneldlls/devices_property/canfdblue-200u.xml
hil/can/zlg/kerneldlls/devices_property/canfdcom-100ie.xml
hil/can/zlg/kerneldlls/devices_property/canfdnet-tcp.xml
hil/can/zlg/kerneldlls/devices_property/canfdnet-udp.xml
hil/can/zlg/kerneldlls/devices_property/canfdnet100-tcp.xml
hil/can/zlg/kerneldlls/devices_property/canfdnet100-udp.xml
hil/can/zlg/kerneldlls/devices_property/canfdnet400u-tcp.xml
hil/can/zlg/kerneldlls/devices_property/canfdnet400u-udp.xml
hil/can/zlg/kerneldlls/devices_property/canfdnet800u-tcp.xml
hil/can/zlg/kerneldlls/devices_property/canfdnet800u-udp.xml
hil/can/zlg/kerneldlls/devices_property/canfdwifi-tcp.xml
hil/can/zlg/kerneldlls/devices_property/canfdwifi-udp.xml
hil/can/zlg/kerneldlls/devices_property/canscope.xml
hil/can/zlg/kerneldlls/devices_property/device_locale_strings.xml
python_can_zlg_kerneldlls-0.0.1.dist-info/LICENSE
python_can_zlg_kerneldlls-0.0.1.dist-info/METADATA
python_can_zlg_kerneldlls-0.0.1.dist-info/WHEEL
python_can_zlg_kerneldlls-0.0.1.dist-info/entry_points.txt
python_can_zlg_kerneldlls-0.0.1.dist-info/top_level.txt
python_can_zlg_kerneldlls-0.0.1.dist-info/RECORD
