Metadata-Version: 2.1
Name: python-can-zlg-kerneldlls
Version: 0.0.1
Summary: 周立功CAN的python-can扩展-kerneldlls
Author: notmmao
Author-email: notmmao@gmail.com
License: MIT
Platform: windows
License-File: LICENSE
